hapflk/InputOutput.py
hapflk/__init__.py
hapflk/data.py
hapflk/flkfreq.py
hapflk/flkpoptree.py
hapflk/hapflk.py
hapflk/hapflkadapt.py
hapflk/nj.py
hapflk/poolflkadapt.py
hapflk/popgen.py
hapflk/utils.py
hapflk-2.1.dist-info/COPYING.txt
hapflk-2.1.dist-info/LICENSE.txt
hapflk-2.1.dist-info/METADATA
hapflk-2.1.dist-info/WHEEL
hapflk-2.1.dist-info/entry_points.txt
hapflk-2.1.dist-info/top_level.txt
hapflk-2.1.dist-info/RECORD
